geotechpy/__init__.py
geotechpy/constants.py
geotechpy/lateral_earth_pressure.py
geotechpy/soil_profile.py
geotechpy/split_layer.py
tests/__init__.py
tests/test_calculations.py
geotechpy-0.0.4.dist-info/LICENSE.txt
geotechpy-0.0.4.dist-info/METADATA
geotechpy-0.0.4.dist-info/WHEEL
geotechpy-0.0.4.dist-info/top_level.txt
geotechpy-0.0.4.dist-info/RECORD
