Metadata-Version: 2.1
Name: geotechpy
Version: 0.0.4
Summary: Python library for geotechnical calculations
Home-page: UNKNOWN
Author: Shawn Hutcherson, P.E.
Author-email: hutcherson.shawn@gmail.com
License: UNKNOWN
Keywords: python,geotechpy,geotechnical,geotech
Platform: UNKNOWN
Classifier: Development Status :: 1 - Planning
Classifier: Intended Audience :: Education
Classifier: Intended Audience :: End Users/Desktop
Classifier: Intended Audience :: Science/Research
Classifier: Programming Language :: Python :: 3
Classifier: Operating System :: OS Independent
Classifier: License :: OSI Approved :: GNU General Public License v3 (GPLv3)
Classifier: Topic :: Scientific/Engineering
Classifier: Natural Language :: English
License-File: LICENSE.txt
Requires-Dist: matplotlib (>=3.8.2)
Requires-Dist: numpy (>=1.26.2)
Requires-Dist: pandas (>=2.1.4)
